3er año/1er cuatri/electronica/TPFINAL CIORCIARI-DASILVA/TFI casi andando/Contador.v
//CONTADOR
module contar_autos(
    input wire clk,
    input wire entrada,
    input wire salida,
    output reg [3:0] espacio
);

initial begin
    espacio = 0;
end

always @(posedge clk) begin
    if (entrada && !salida && espacio < 7)
        espacio <= espacio + 1;
    else if (salida && !entrada && espacio > 0)
        espacio <= espacio - 1;
end
endmodule

3er año/1er cuatri/electronica/TPFINAL CIORCIARI-DASILVA/TFI casi andando/Detector.v
//Detectamos señales de entradadas de auto
/*
ENTRADA
S0: no se detectan pulsos
S1: detectamos boton A
S2:detectamos boton A y B
S3: detectamos boton B (sin A) 
S3->S0 Z=1

SALIDA
S3:detectamos boton B
S2: detectamos boton A y B
S1: detectamos boton A
S1->S0
S0: no se detectan pulsos (salio un auto) 
*/
module detector(
    input wire clk,
    input botonA,
    input botonB,
    output reg entrada,
    output reg salida
);

localparam S0=2'b00; //no detectamos pulsos
localparam S1=2'b10; // detectamos boton A
localparam S2=2'b11; //detectamos botones A y B
localparam S3=2'b01; //detectamos B

reg [1:0] state, nextstate;

always@(posedge clk)
begin 
    state <= nextstate;
end

always @* begin
    entrada = 0;
    salida = 0;
    nextstate = state;
    case(state)
    S0: begin
        if({botonA,botonB}==2'b10)
           nextstate = S1; // detectamos A
        else if({botonA,botonB}==2'b01)
            nextstate = S3; // detectamos solo B (posible salida)
    end
    S1: begin
        if ({botonA,botonB}==2'b11)
            nextstate = S2; // detectamos A y B
        else if({botonA,botonB}==2'b00) begin
            nextstate = S0; // confirmamos salida
            salida = 1; // aumentamos contador
        end
    end
    S2: begin
        if({botonA,botonB}==2'b01)
            nextstate = S3; // detectamos solo B (transición correcta)
        else if({botonA,botonB}==2'b10)
            nextstate = S1; // regresamos a solo A
    end
    S3: begin
        if({botonA,botonB}==2'b00) begin
            nextstate = S0; // confirmamos entrada
            entrada = 1; // contamos
        end else if({botonA,botonB}==2'b11)
            nextstate = S2; // regresamos a A y B
    end
    default: begin 
        nextstate = S0; 
        entrada = 0; 
        salida = 0; 
    end
    endcase
end
endmodule

3er año/1er cuatri/electronica/TPFINAL CIORCIARI-DASILVA/TFI casi andando/Antirebote.v
module antirrebote(
    input wire clk,
    input wire senal_entrada,  
    output reg salida_limpia   
);
    reg [19:0] contador;      
    reg salida_reg;

    initial begin
        salida_limpia = 0;
        contador = 0;
        salida_reg = 0;
    end

    always @(posedge clk) begin
        if (senal_entrada != salida_reg) begin
            contador <= 20'b0; // Reiniciamos el contador si hay un cambio en la señal
            salida_reg <= senal_entrada; // Actualizamos el registro de la señal
        end else if (contador < 20'd100000) begin // Ajustamos el tiempo de estabilización
            contador <= contador + 1; // Incrementamos el contador
        end else begin
            salida_limpia <= salida_reg; // Actualizamos la salida limpia solo si el contador llega al límite
        end
    end
endmodule

3er año/1er cuatri/electronica/TPFINAL CIORCIARI-DASILVA/TFI casi andando/Sensores.v
module sensores(
    input wire clk,
    input botonA,
    input botonB,
    output wire botonA_estable,
    output wire botonB_estable
);

antirrebote antirreboteA(
    .clk(clk),
    .senal_entrada(botonA),
    .salida_limpia(botonA_estable)
);

antirrebote antirreboteB(
    .clk(clk),
    .senal_entrada(botonB),
    .salida_limpia(botonB_estable)
);

endmodule

3er año/1er cuatri/electronica/TPFINAL CIORCIARI-DASILVA/TFI casi andando/TFI.v
module TFI(
    input wire CLK,
    input BTN1,//BotonA
    input BTN2, //BotonB
    output wire LED3,
    output wire LED2,
    output wire LED1,
    output wire LED0
);

wire botonA_estable, botonB_estable;
wire entrada, salida;
wire [3:0] espacio;




sensores sensores_instacia(
    .clk(CLK),
    .botonA(BTN1),
    .botonB(BTN2),
    .botonA_estable(botonA_estable),
    .botonB_estable(botonB_estable)
);

detector detector_instancia(
    .clk(CLK),
    .botonA(botonA_estable),
    .botonB(botonB_estable),
    .entrada(entrada),
    .salida(salida)
);

contar_autos contador_instancia(
    .clk(CLK),
    .entrada(entrada),
    .salida(salida),
    .espacio(espacio)
);
assign {LED3,LED2,LED1,LED0}={1'b0,espacio}; 
endmodule

3er año/1er cuatri/electronica/TPFINAL CIORCIARI-DASILVA/TFI casi andando/TFI_tb.v
`timescale 1ns / 1ps

module TFI_tb;

    // Entradas
    reg clk;
    reg botonA;
    reg botonB;

    // Salidas
    wire [3:0] leds;

    // Instancia del módulo TFI
    TFI uut (
        .CLK(clk),       // Conecta el reloj
        .BTN1(botonA),   // Conecta el botón A
        .BTN2(botonB),   // Conecta el botón B
        .LED3(leds[3]),  // Conecta el LED3
        .LED2(leds[2]),  // Conecta el LED2
        .LED1(leds[1]),  // Conecta el LED1
        .LED0(leds[0])   // Conecta el LED0
    );

    // Generador de reloj
    always #10 clk = ~clk; // Reloj de 50 MHz (20 ns por ciclo)

    initial begin
        // Inicialización del archivo .vcd
        $dumpfile("TFI_tb.vcd"); // Nombre del archivo .vcd
        $dumpvars(0, uut); // Registra solo las señales del módulo principal TFI

        // Inicialización
        clk = 0;
        botonA = 0;
        botonB = 0;

        // Simulamos el patrón de ingreso de un auto
        #200 botonA = 1;  // Presionamos botonA (20 us)
        #20000 botonB = 1;  // Presionamos botonB (20 us)
        #200 botonA = 0;  // Soltamos botonA (20 us)
        #20000 botonB = 0;  // Soltamos botonB (20 us)

        // Esperamos para observar el resultado
        #100000;

        // Simulamos el patrón de egreso de un auto
        #20000 botonB = 1;  // Presionamos botonB (20 us)
        #20000 botonA = 1;  // Presionamos botonA (20 us)
        #20000 botonB = 0;  // Soltamos botonB (20 us)
        #20000 botonA = 0;  // Soltamos botonA (20 us)

        // Esperamos para observar el resultado
        #100000;

        // Finalizamos la simulación
        $finish; // Finaliza la simulación correctamente
    end
endmodule

3er año/1er cuatri/electronica/TPFINAL CIORCIARI-DASILVA/TFI casi andando/TFI_tb.vcd
$date
	Sat Jun 21 17:57:27 2025
$end
$version
	Icarus Verilog
$end
$timescale
	1ps
$end
$scope module TFI_tb $end
$scope module uut $end
$var wire 1 ! BTN1 $end
$var wire 1 " BTN2 $end
$var wire 1 # CLK $end
$var wire 1 $ salida $end
$var wire 4 % espacio [3:0] $end
$var wire 1 & entrada $end
$var wire 1 ' botonB_estable $end
$var wire 1 ( botonA_estable $end
$var wire 1 ) LED3 $end
$var wire 1 * LED2 $end
$var wire 1 + LED1 $end
$var wire 1 , LED0 $end
$scope module contador_instancia $end
$var wire 1 # clk $end
$var wire 1 $ salida $end
$var wire 1 & entrada $end
$var reg 4 - espacio [3:0] $end
$upscope $end
$scope module detector_instancia $end
$var wire 1 # clk $end
$var wire 1 ' botonB $end
$var wire 1 ( botonA $end
$var parameter 2 . S0 $end
$var parameter 2 / S1 $end
$var parameter 2 0 S2 $end
$var parameter 2 1 S3 $end
$var reg 1 & entrada $end
$var reg 2 2 nextstate [1:0] $end
$var reg 1 $ salida $end
$var reg 2 3 state [1:0] $end
$upscope $end
$scope module sensores_instacia $end
$var wire 1 ! botonA $end
$var wire 1 " botonB $end
$var wire 1 # clk $end
$var wire 1 ' botonB_estable $end
$var wire 1 ( botonA_estable $end
$scope module antirreboteA $end
$var wire 1 # clk $end
$var wire 1 ! senal_entrada $end
$var reg 20 4 contador [19:0] $end
$var reg 1 ( salida_limpia $end
$var reg 1 5 salida_reg $end
$upscope $end
$scope module antirreboteB $end
$var wire 1 # clk $end
$var wire 1 " senal_entrada $end
$var reg 20 6 contador [19:0] $end
$var reg 1 ' salida_limpia $end
$var reg 1 7 salida_reg $end
$upscope $end
$upscope $end
$upscope $end
$upscope $end
$enddefinitions $end
$comment Show the parameter values. $end
$dumpall
b1 1
b11 0
b10 /
b0 .
$end
#0
$dumpvars
07
b0 6
05
b0 4
bx 3
b0 2
b0 -
0,
0+
0*
0)
0(
0'
0&
b0 %
0$
0#
0"
0!
$end
#10000
b1 4
b1 6
b0 3
1#
#20000
0#
#30000
b10 6
b10 4
1#
#40000
0#
#50000
b11 4
b11 6
1#
#60000
0#
#70000
b100 6
b100 4
1#
#80000
0#
#90000
b101 4
b101 6
1#
#100000
0#
#110000
b110 6
b110 4
1#
#120000
0#
#130000
b111 4
b111 6
1#
#140000
0#
#150000
b1000 6
b1000 4
1#
#160000
0#
#170000
b1001 4
b1001 6
1#
#180000
0#
#190000
b1010 6
b1010 4
1#
#200000
0#
1!
#210000
15
b0 4
b1011 6
1#
#220000
0#
#230000
b1100 6
b1 4
1#
#240000
0#
#250000
b10 4
b1101 6
1#
#260000
0#
#270000
b1110 6
b11 4
1#
#280000
0#
#290000
b100 4
b1111 6
1#
#300000
0#
#310000
b10000 6
b101 4
1#
#320000
0#
#330000
b110 4
b10001 6
1#
#340000
0#
#350000
b10010 6
b111 4
1#
#360000
0#
#370000
b1000 4
b10011 6
1#
#380000
0#
#390000
b10100 6
b1001 4
1#
#400000
0#
#410000
b1010 4
b10101 6
1#
#420000
0#
#430000
b10110 6
b1011 4
1#
#440000
0#
#450000
b1100 4
b10111 6
1#
#460000
0#
#470000
b11000 6
b1101 4
1#
#480000
0#
#490000
b1110 4
b11001 6
1#
#500000
0#
#510000
b11010 6
b1111 4
1#
#520000
0#
#530000
b10000 4
b11011 6
1#
#540000
0#
#550000
b11100 6
b10001 4
1#
#560000
0#
#570000
b10010 4
b11101 6
1#
#580000
0#
#590000
b11110 6
b10011 4
1#
#600000
0#
#610000
b10100 4
b11111 6
1#
#620000
0#
#630000
b100000 6
b10101 4
1#
#640000
0#
#650000
b10110 4
b100001 6
1#
#660000
0#
#670000
b100010 6
b10111 4
1#
#680000
0#
#690000
b11000 4
b100011 6
1#
#700000
0#
#710000
b100100 6
b11001 4
1#
#720000
0#
#730000
b11010 4
b100101 6
1#
#740000
0#
#750000
b100110 6
b11011 4
1#
#760000
0#
#770000
b11100 4
b100111 6
1#
#780000
0#
#790000
b101000 6
b11101 4
1#
#800000
0#
#810000
b11110 4
b101001 6
1#
#820000
0#
#830000
b101010 6
b11111 4
1#
#840000
0#
#850000
b100000 4
b101011 6
1#
#860000
0#
#870000
b101100 6
b100001 4
1#
#880000
0#
#890000
b100010 4
b101101 6
1#
#900000
0#
#910000
b101110 6
b100011 4
1#
#920000
0#
#930000
b100100 4
b101111 6
1#
#940000
0#
#950000
b110000 6
b100101 4
1#
#960000
0#
#970000
b100110 4
b110001 6
1#
#980000
0#
#990000
b110010 6
b100111 4
1#
#1000000
0#
#1010000
b101000 4
b110011 6
1#
#1020000
0#
#1030000
b110100 6
b101001 4
1#
#1040000
0#
#1050000
b101010 4
b110101 6
1#
#1060000
0#
#1070000
b110110 6
b101011 4
1#
#1080000
0#
#1090000
b101100 4
b110111 6
1#
#1100000
0#
#1110000
b111000 6
b101101 4
1#
#1120000
0#
#1130000
b101110 4
b111001 6
1#
#1140000
0#
#1150000
b111010 6
b101111 4
1#
#1160000
0#
#1170000
b110000 4
b111011 6
1#
#1180000
0#
#1190000
b111100 6
b110001 4
1#
#1200000
0#
#1210000
b110010 4
b111101 6
1#
#1220000
0#
#1230000
b111110 6
b110011 4
1#
#1240000
0#
#1250000
b110100 4
b111111 6
1#
#1260000
0#
#1270000
b1000000 6
b110101 4
1#
#1280000
0#
#1290000
b110110 4
b1000001 6
1#
#1300000
0#
#1310000
b1000010 6
b110111 4
1#
#1320000
0#
#1330000
b111000 4
b1000011 6
1#
#1340000
0#
#1350000
b1000100 6
b111001 4
1#
#1360000
0#
#1370000
b111010 4
b1000101 6
1#
#1380000
0#
#1390000
b1000110 6
b111011 4
1#
#1400000
0#
#1410000
b111100 4
b1000111 6
1#
#1420000
0#
#1430000
b1001000 6
b111101 4
1#
#1440000
0#
#1450000
b111110 4
b1001001 6
1#
#1460000
0#
#1470000
b1001010 6
b111111 4
1#
#1480000
0#
#1490000
b1000000 4
b1001011 6
1#
#1500000
0#
#1510000
b1001100 6
b1000001 4
1#
#1520000
0#
#1530000
b1000010 4
b1001101 6
1#
#1540000
0#
#1550000
b1001110 6
b1000011 4
1#
#1560000
0#
#1570000
b1000100 4
b1001111 6
1#
#1580000
0#
#1590000
b1010000 6
b1000101 4
1#
#1600000
0#
#1610000
b1000110 4
b1010001 6
1#
#1620000
0#
#1630000
b1010010 6
b1000111 4
1#
#1640000
0#
#1650000
b1001000 4
b1010011 6
1#
#1660000
0#
#1670000
b1010100 6
b1001001 4
1#
#1680000
0#
#1690000
b1001010 4
b1010101 6
1#
#1700000
0#
#1710000
b1010110 6
b1001011 4
1#
#1720000
0#
#1730000
b1001100 4
b1010111 6
1#
#1740000
0#
#1750000
b1011000 6
b1001101 4
1#
#1760000
0#
#1770000
b1001110 4
b1011001 6
1#
#1780000
0#
#1790000
b1011010 6
b1001111 4
1#
#1800000
0#
#1810000
b1010000 4
b1011011 6
1#
#1820000
0#
#1830000
b1011100 6
b1010001 4
1#
#1840000
0#
#1850000
b1010010 4
b1011101 6
1#
#1860000
0#
#1870000
b1011110 6
b1010011 4
1#
#1880000
0#
#1890000
b1010100 4
b1011111 6
1#
#1900000
0#
#1910000
b1100000 6
b1010101 4
1#
#1920000
0#
#1930000
b1010110 4
b1100001 6
1#
#1940000
0#
#1950000
b1100010 6
b1010111 4
1#
#1960000
0#
#1970000
b1011000 4
b1100011 6
1#
#1980000
0#
#1990000
b1100100 6
b1011001 4
1#
#2000000
0#
#2010000
b1011010 4
b1100101 6
1#
#2020000
0#
#2030000
b1100110 6
b1011011 4
1#
#2040000
0#
#2050000
b1011100 4
b1100111 6
1#
#2060000
0#
#2070000
b1101000 6
b1011101 4
1#
#2080000
0#
#2090000
b1011110 4
b1101001 6
1#
#2100000
0#
#2110000
b1101010 6
b1011111 4
1#
#2120000
0#
#2130000
b1100000 4
b1101011 6
1#
#2140000
0#
#2150000
b1101100 6
b1100001 4
1#
#2160000
0#
#2170000
b1100010 4
b1101101 6
1#
#2180000
0#
#2190000
b1101110 6
b1100011 4
1#
#2200000
0#
#2210000
b1100100 4
b1101111 6
1#
#2220000
0#
#2230000
b1110000 6
b1100101 4
1#
#2240000
0#
#2250000
b1100110 4
b1110001 6
1#
#2260000
0#
#2270000
b1110010 6
b1100111 4
1#
#2280000
0#
#2290000
b1101000 4
b1110011 6
1#
#2300000
0#
#2310000
b1110100 6
b1101001 4
1#
#2320000
0#
#2330000
b1101010 4
b1110101 6
1#
#2340000
0#
#2350000
b1110110 6
b1101011 4
1#
#2360000
0#
#2370000
b1101100 4
b1110111 6
1#
#2380000
0#
#2390000
b1111000 6
b1101101 4
1#
#2400000
0#
#2410000
b1101110 4
b1111001 6
1#
#2420000
0#
#2430000
b1111010 6
b1101111 4
1#
#2440000
0#
#2450000
b1110000 4
b1111011 6
1#
#2460000
0#
#2470000
b1111100 6
b1110001 4
1#
#2480000
0#
#2490000
b1110010 4
b1111101 6
1#
#2500000
0#
#2510000
b1111110 6
b1110011 4
1#
#2520000
0#
#2530000
b1110100 4
b1111111 6
1#
#2540000
0#
#2550000
b10000000 6
b1110101 4
1#
#2560000
0#
#2570000
b1110110 4
b10000001 6
1#
#2580000
0#
#2590000
b10000010 6
b1110111 4
1#
#2600000
0#
#2610000
b1111000 4
b10000011 6
1#
#2620000
0#
#2630000
b10000100 6
b1111001 4
1#
#2640000
0#
#2650000
b1111010 4
b10000101 6
1#
#2660000
0#
#2670000
b10000110 6
b1111011 4
1#
#2680000
0#
#2690000
b1111100 4
b10000111 6
1#
#2700000
0#
#2710000
b10001000 6
b1111101 4
1#
#2720000
0#
#2730000
b1111110 4
b10001001 6
1#
#2740000
0#
#2750000
b10001010 6
b1111111 4
1#
#2760000
0#
#2770000
b10000000 4
b10001011 6
1#
#2780000
0#
#2790000
b10001100 6
b10000001 4
1#
#2800000
0#
#2810000
b10000010 4
b10001101 6
1#
#2820000
0#
#2830000
b10001110 6
b10000011 4
1#
#2840000
0#
#2850000
b10000100 4
b10001111 6
1#
#2860000
0#
#2870000
b10010000 6
b10000101 4
1#
#2880000
0#
#2890000
b10000110 4
b10010001 6
1#
#2900000
0#
#2910000
b10010010 6
b10000111 4
1#
#2920000
0#
#2930000
b10001000 4
b10010011 6
1#
#2940000
0#
#2950000
b10010100 6
b10001001 4
1#
#2960000
0#
#2970000
b10001010 4
b10010101 6
1#
#2980000
0#
#2990000
b10010110 6
b10001011 4
1#
#3000000
0#
#3010000
b10001100 4
b10010111 6
1#
#3020000
0#
#3030000
b10011000 6
b10001101 4
1#
#3040000
0#
#3050000
b10001110 4
b10011001 6
1#
#3060000
0#
#3070000
b10011010 6
b10001111 4
1#
#3080000
0#
#3090000
b10010000 4
b10011011 6
1#
#3100000
0#
#3110000
b10011100 6
b10010001 4
1#
#3120000
0#
#3130000
b10010010 4
b10011101 6
1#
#3140000
0#
#3150000
b10011110 6
b10010011 4
1#
#3160000
0#
#3170000
b10010100 4
b10011111 6
1#
#3180000
0#
#3190000
b10100000 6
b10010101 4
1#
#3200000
0#
#3210000
b10010110 4
b10100001 6
1#
#3220000
0#
#3230000
b10100010 6
b10010111 4
1#
#3240000
0#
#3250000
b10011000 4
b10100011 6
1#
#3260000
0#
#3270000
b10100100 6
b10011001 4
1#
#3280000
0#
#3290000
b10011010 4
b10100101 6
1#
#3300000
0#
#3310000
b10100110 6
b10011011 4
1#
#3320000
0#
#3330000
b10011100 4
b10100111 6
1#
#3340000
0#
#3350000
b10101000 6
b10011101 4
1#
#3360000
0#
#3370000
b10011110 4
b10101001 6
1#
#3380000
0#
#3390000
b10101010 6
b10011111 4
1#
#3400000
0#
#3410000
b10100000 4
b10101011 6
1#
#3420000
0#
#3430000
b10101100 6
b10100001 4
1#
#3440000
0#
#3450000
b10100010 4
b10101101 6
1#
#3460000
0#
#3470000
b10101110 6
b10100011 4
1#
#3480000
0#
#3490000
b10100100 4
b10101111 6
1#
#3500000
0#
#3510000
b10110000 6
b10100101 4
1#
#3520000
0#
#3530000
b10100110 4
b10110001 6
1#
#3540000
0#
#3550000
b10110010 6
b10100111 4
1#
#3560000
0#
#3570000
b10101000 4
b10110011 6
1#
#3580000
0#
#3590000
b10110100 6
b10101001 4
1#
#3600000
0#
#3610000
b10101010 4
b10110101 6
1#
#3620000
0#
#3630000
b10110110 6
b10101011 4
1#
#3640000
0#
#3650000
b10101100 4
b10110111 6
1#
#3660000
0#
#3670000
b10111000 6
b10101101 4
1#
#3680000
0#
#3690000
b10101110 4
b10111001 6
1#
#3700000
0#
#3710000
b10111010 6
b10101111 4
1#
#3720000
0#
#3730000
b10110000 4
b10111011 6
1#
#3740000
0#
#3750000
b10111100 6
b10110001 4
1#
#3760000
0#
#3770000
b10110010 4
b10111101 6
1#
#3780000
0#
#3790000
b10111110 6
b10110011 4
1#
#3800000
0#
#3810000
b10110100 4
b10111111 6
1#
#3820000
0#
#3830000
b11000000 6
b10110101 4
1#
#3840000
0#
#3850000
b10110110 4
b11000001 6
1#
#3860000
0#
#3870000
b11000010 6
b10110111 4
1#
#3880000
0#
#3890000
b10111000 4
b11000011 6
1#
#3900000
0#
#3910000
b11000100 6
b10111001 4
1#
#3920000
0#
#3930000
b10111010 4
b11000101 6
1#
#3940000
0#
#3950000
b11000110 6
b10111011 4
1#
#3960000
0#
#3970000
b10111100 4
b11000111 6
1#
#3980000
0#
#3990000
b11001000 6
b10111101 4
1#
#4000000
0#
#4010000
b10111110 4
b11001001 6
1#
#4020000
0#
#4030000
b11001010 6
b10111111 4
1#
#4040000
0#
#4050000
b11000000 4
b11001011 6
1#
#4060000
0#
#4070000
b11001100 6
b11000001 4
1#
#4080000
0#
#4090000
b11000010 4
b11001101 6
1#
#4100000
0#
#4110000
b11001110 6
b11000011 4
1#
#4120000
0#
#4130000
b11000100 4
b11001111 6
1#
#4140000
0#
#4150000
b11010000 6
b11000101 4
1#
#4160000
0#
#4170000
b11000110 4
b11010001 6
1#
#4180000
0#
#4190000
b11010010 6
b11000111 4
1#
#4200000
0#
#4210000
b11001000 4
b11010011 6
1#
#4220000
0#
#4230000
b11010100 6
b11001001 4
1#
#4240000
0#
#4250000
b11001010 4
b11010101 6
1#
#4260000
0#
#4270000
b11010110 6
b11001011 4
1#
#4280000
0#
#4290000
b11001100 4
b11010111 6
1#
#4300000
0#
#4310000
b11011000 6
b11001101 4
1#
#4320000
0#
#4330000
b11001110 4
b11011001 6
1#
#4340000
0#
#4350000
b11011010 6
b11001111 4
1#
#4360000
0#
#4370000
b11010000 4
b11011011 6
1#
#4380000
0#
#4390000
b11011100 6
b11010001 4
1#
#4400000
0#
#4410000
b11010010 4
b11011101 6
1#
#4420000
0#
#4430000
b11011110 6
b11010011 4
1#
#4440000
0#
#4450000
b11010100 4
b11011111 6
1#
#4460000
0#
#4470000
b11100000 6
b11010101 4
1#
#4480000
0#
#4490000
b11010110 4
b11100001 6
1#
#4500000
0#
#4510000
b11100010 6
b11010111 4
1#
#4520000
0#
#4530000
b11011000 4
b11100011 6
1#
#4540000
0#
#4550000
b11100100 6
b11011001 4
1#
#4560000
0#
#4570000
b11011010 4
b11100101 6
1#
#4580000
0#
#4590000
b11100110 6
b11011011 4
1#
#4600000
0#
#4610000
b11011100 4
b11100111 6
1#
#4620000
0#
#4630000
b11101000 6
b11011101 4
1#
#4640000
0#
#4650000
b11011110 4
b11101001 6
1#
#4660000
0#
#4670000
b11101010 6
b11011111 4
1#
#4680000
0#
#4690000
b11100000 4
b11101011 6
1#
#4700000
0#
#4710000
b11101100 6
b11100001 4
1#
#4720000
0#
#4730000
b11100010 4
b11101101 6
1#
#4740000
0#
#4750000
b11101110 6
b11100011 4
1#
#4760000
0#
#4770000
b11100100 4
b11101111 6
1#
#4780000
0#
#4790000
b11110000 6
b11100101 4
1#
#4800000
0#
#4810000
b11100110 4
b11110001 6
1#
#4820000
0#
#4830000
b11110010 6
b11100111 4
1#
#4840000
0#
#4850000
b11101000 4
b11110011 6
1#
#4860000
0#
#4870000
b11110100 6
b11101001 4
1#
#4880000
0#
#4890000
b11101010 4
b11110101 6
1#
#4900000
0#
#4910000
b11110110 6
b11101011 4
1#
#4920000
0#
#4930000
b11101100 4
b11110111 6
1#
#4940000
0#
#4950000
b11111000 6
b11101101 4
1#
#4960000
0#
#4970000
b11101110 4
b11111001 6
1#
#4980000
0#
#4990000
b11111010 6
b11101111 4
1#
#5000000
0#
#5010000
b11110000 4
b11111011 6
1#
#5020000
0#
#5030000
b11111100 6
b11110001 4
1#
#5040000
0#
#5050000
b11110010 4
b11111101 6
1#
#5060000
0#
#5070000
b11111110 6
b11110011 4
1#
#5080000
0#
#5090000
b11110100 4
b11111111 6
1#
#5100000
0#
#5110000
b100000000 6
b11110101 4
1#
#5120000
0#
#5130000
b11110110 4
b100000001 6
1#
#5140000
0#
#5150000
b100000010 6
b11110111 4
1#
#5160000
0#
#5170000
b11111000 4
b100000011 6
1#
#5180000
0#
#5190000
b100000100 6
b11111001 4
1#
#5200000
0#
#5210000
b11111010 4
b100000101 6
1#
#5220000
0#
#5230000
b100000110 6
b11111011 4
1#
#5240000
0#
#5250000
b11111100 4
b100000111 6
1#
#5260000
0#
#5270000
b100001000 6
b11111101 4
1#
#5280000
0#
#5290000
b11111110 4
b100001001 6
1#
#5300000
0#
#5310000
b100001010 6
b11111111 4
1#
#5320000
0#
#5330000
b100000000 4
b100001011 6
1#
#5340000
0#
#5350000
b100001100 6
b100000001 4
1#
#5360000
0#
#5370000
b100000010 4
b100001101 6
1#
#5380000
0#
#5390000
b100001110 6
b100000011 4
1#
#5400000
0#
#5410000
b100000100 4
b100001111 6
1#
#5420000
0#
#5430000
b100010000 6
b100000101 4
1#
#5440000
0#
#5450000
b100000110 4
b100010001 6
1#
#5460000
0#
#5470000
b100010010 6
b100000111 4
1#
#5480000
0#
#5490000
b100001000 4
b100010011 6
1#
#5500000
0#
#5510000
b100010100 6
b100001001 4
1#
#5520000
0#
#5530000
b100001010 4
b100010101 6
1#
#5540000
0#
#5550000
b100010110 6
b100001011 4
1#
#5560000
0#
#5570000
b100001100 4
b100010111 6
1#
#5580000
0#
#5590000
b100011000 6
b100001101 4
1#
#5600000
0#
#5610000
b100001110 4
b100011001 6
1#
#5620000
0#
#5630000
b100011010 6
b100001111 4
1#
#5640000
0#
#5650000
b100010000 4
b100011011 6
1#
#5660000
0#
#5670000
b100011100 6
b100010001 4
1#
#5680000
0#
#5690000
b100010010 4
b100011101 6
1#
#5700000
0#
#5710000
b100011110 6
b100010011 4
1#
#5720000
0#
#5730000
b100010100 4
b100011111 6
1#
#5740000
0#
#5750000
b100100000 6
b100010101 4
1#
#5760000
0#
#5770000
b100010110 4
b100100001 6
1#
#5780000
0#
#5790000
b100100010 6
b100010111 4
1#
#5800000
0#
#5810000
b100011000 4
b100100011 6
1#
#5820000
0#
#5830000
b100100100 6
b100011001 4
1#
#5840000
0#
#5850000
b100011010 4
b100100101 6
1#
#5860000
0#
#5870000
b100100110 6
b100011011 4
1#
#5880000
0#
#5890000
b100011100 4
b100100111 6
1#
#5900000
0#
#5910000
b100101000 6
b100011101 4
1#
#5920000
0#
#5930000
b100011110 4
b100101001 6
1#
#5940000
0#
#5950000
b100101010 6
b100011111 4
1#
#5960000
0#
#5970000
b100100000 4
b100101011 6
1#
#5980000
0#
#5990000
b100101100 6
b100100001 4
1#
#6000000
0#
#6010000
b100100010 4
b100101101 6
1#
#6020000
0#
#6030000
b100101110 6
b100100011 4
1#
#6040000
0#
#6050000
b100100100 4
b100101111 6
1#
#6060000
0#
#6070000
b100110000 6
b100100101 4
1#
#6080000
0#
#6090000
b100100110 4
b100110001 6
1#
#6100000
0#
#6110000
b100110010 6
b100100111 4
1#
#6120000
0#
#6130000
b100101000 4
b100110011 6
1#
#6140000
0#
#6150000
b100110100 6
b100101001 4
1#
#6160000
0#
#6170000
b100101010 4
b100110101 6
1#
#6180000
0#
#6190000
b100110110 6
b100101011 4
1#
#6200000
0#
#6210000
b100101100 4
b100110111 6
1#
#6220000
0#
#6230000
b100111000 6
b100101101 4
1#
#6240000
0#
#6250000
b100101110 4
b100111001 6
1#
#6260000
0#
#6270000
b100111010 6
b100101111 4
1#
#6280000
0#
#6290000
b100110000 4
b100111011 6
1#
#6300000
0#
#6310000
b100111100 6
b100110001 4
1#
#6320000
0#
#6330000
b100110010 4
b100111101 6
1#
#6340000
0#
#6350000
b100111110 6
b100110011 4
1#
#6360000
0#
#6370000
b100110100 4
b100111111 6
1#
#6380000
0#
#6390000
b101000000 6
b100110101 4
1#
#6400000
0#
#6410000
b100110110 4
b101000001 6
1#
#6420000
0#
#6430000
b101000010 6
b100110111 4
1#
#6440000
0#
#6450000
b100111000 4
b101000011 6
1#
#6460000
0#
#6470000
b101000100 6
b100111001 4
1#
#6480000
0#
#6490000
b100111010 4
b101000101 6
1#
#6500000
0#
#6510000
b101000110 6
b100111011 4
1#
#6520000
0#
#6530000
b100111100 4
b101000111 6
1#
#6540000
0#
#6550000
b101001000 6
b100111101 4
1#
#6560000
0#
#6570000
b100111110 4
b101001001 6
1#
#6580000
0#
#6590000
b101001010 6
b100111111 4
1#
#6600000
0#
#6610000
b101000000 4
b101001011 6
1#
#6620000
0#
#6630000
b101001100 6
b101000001 4
1#
#6640000
0#
#6650000
b101000010 4
b101001101 6
1#
#6660000
0#
#6670000
b101001110 6
b101000011 4
1#
#6680000
0#
#6690000
b101000100 4
b101001111 6
1#
#6700000
0#
#6710000
b101010000 6
b101000101 4
1#
#6720000
0#
#6730000
b101000110 4
b101010001 6
1#
#6740000
0#
#6750000
b101010010 6
b101000111 4
1#
#6760000
0#
#6770000
b101001000 4
b101010011 6
1#
#6780000
0#
#6790000
b101010100 6
b101001001 4
1#
#6800000
0#
#6810000
b101001010 4
b101010101 6
1#
#6820000
0#
#6830000
b101010110 6
b101001011 4
1#
#6840000
0#
#6850000
b101001100 4
b101010111 6
1#
#6860000
0#
#6870000
b101011000 6
b101001101 4
1#
#6880000
0#
#6890000
b101001110 4
b101011001 6
1#
#6900000
0#
#6910000
b101011010 6
b101001111 4
1#
#6920000
0#
#6930000
b101010000 4
b101011011 6
1#
#6940000
0#
#6950000
b101011100 6
b101010001 4
1#
#6960000
0#
#6970000
b101010010 4
b101011101 6
1#
#6980000
0#
#6990000
b101011110 6
b101010011 4
1#
#7000000
0#
#7010000
b101010100 4
b101011111 6
1#
#7020000
0#
#7030000
b101100000 6
b101010101 4
1#
#7040000
0#
#7050000
b101010110 4
b101100001 6
1#
#7060000
0#
#7070000
b101100010 6
b101010111 4
1#
#7080000
0#
#7090000
b101011000 4
b101100011 6
1#
#7100000
0#
#7110000
b101100100 6
b101011001 4
1#
#7120000
0#
#7130000
b101011010 4
b101100101 6
1#
#7140000
0#
#7150000
b101100110 6
b101011011 4
1#
#7160000
0#
#7170000
b101011100 4
b101100111 6
1#
#7180000
0#
#7190000
b101101000 6
b101011101 4
1#
#7200000
0#
#7210000
b101011110 4
b101101001 6
1#
#7220000
0#
#7230000
b101101010 6
b101011111 4
1#
#7240000
0#
#7250000
b101100000 4
b101101011 6
1#
#7260000
0#
#7270000
b101101100 6
b101100001 4
1#
#7280000
0#
#7290000
b101100010 4
b101101101 6
1#
#7300000
0#
#7310000
b101101110 6
b101100011 4
1#
#7320000
0#
#7330000
b101100100 4
b101101111 6
1#
#7340000
0#
#7350000
b101110000 6
b101100101 4
1#
#7360000
0#
#7370000
b101100110 4
b101110001 6
1#
#7380000
0#
#7390000
b101110010 6
b101100111 4
1#
#7400000
0#
#7410000
b101101000 4
b101110011 6
1#
#7420000
0#
#7430000
b101110100 6
b101101001 4
1#
#7440000
0#
#7450000
b101101010 4
b101110101 6
1#
#7460000
0#
#7470000
b101110110 6
b101101011 4
1#
#7480000
0#
#7490000
b101101100 4
b101110111 6
1#
#7500000
0#
#7510000
b101111000 6
b101101101 4
1#
#7520000
0#
#7530000
b101101110 4
b101111001 6
1#
#7540000
0#
